byted_overpass_data_ecom_scl_offline_task_faas/__init__.py
byted_overpass_data_ecom_scl_offline_task_faas-0.0.1.dist-info/METADATA
byted_overpass_data_ecom_scl_offline_task_faas-0.0.1.dist-info/WHEEL
byted_overpass_data_ecom_scl_offline_task_faas-0.0.1.dist-info/top_level.txt
byted_overpass_data_ecom_scl_offline_task_faas-0.0.1.dist-info/RECORD
