Metadata-Version: 2.1
Name: byted-overpass-data-ecom-scl-offline-task-faas
Version: 0.0.1
Summary: A simple package named byted_overpass_data_ecom_scl_offline_task_faas
Home-page: https://github.com/artifact/byted_overpass_data_ecom_scl_offline_task_faas.git
Author: artifact
Author-email: artifact@example.com
License: UNKNOWN
Platform: UNKNOWN
Classifier: Programming Language :: Python :: 3
Classifier: License :: OSI Approved :: MIT License
Classifier: Operating System :: OS Independent
